discord_ios/__init__.py
discord_ios/identify.py
discord_ios-1.1.1.dist-info/METADATA
discord_ios-1.1.1.dist-info/WHEEL
discord_ios-1.1.1.dist-info/top_level.txt
discord_ios-1.1.1.dist-info/RECORD
